{"_type":"export","__export_format":4,"__export_date":"2021-07-29T20:54:38.558Z","__export_source":"insomnia.desktop.app:v2021.4.1","resources":[{"_id":"req_7de73bcd6378410d96db1c8837143831","parentId":"fld_a75ad14808044849921ea706216d4d7f","modified":1626809187614,"created":1626799781885,"url":"http://localhost:4999/api/faturastotvs","name":"Faturas Totvs","description":"","method":"GET","body":{},"parameters":[{"name":"quitado","value":"N","id":"pair_a2c0c894af46429b9b8d994666edfa47"},{"name":"dataini","value":"2021-01-221","id":"pair_92fb98eceb2a4ea19505cbc982a00fb6"},{"name":"datafin","value":"2021-07-22","id":"pair_c6773d0e7f1e4495a216dda36dce4894"},{"name":"pagina_nro","value":"1","id":"pair_4ae310fc4eb7499ea05d84b7c276722c"},{"name":"pagina_tam","value":"20","id":"pair_d60e0a02d0654df5b1a2ebd9ae6441e1"}],"headers":[],"authentication":{},"metaSortKey":-1626799781886,"isPrivate":false,"settingStoreCookies":true,"settingSendCookies":true,"settingDisableRenderRequestBody":false,"settingEncodeUrl":true,"settingRebuildPath":true,"settingFollowRedirects":"global","_type":"request"},{"_id":"fld_a75ad14808044849921ea706216d4d7f","parentId":"wrk_c8a47759fa464349907c3e1809f8adf6","modified":1626799730751,"created":1626799700659,"name":"APP_Portfolio","description":"","environment":{},"environmentPropertyOrder":null,"metaSortKey":-1626799700659,"_type":"request_group"},{"_id":"wrk_c8a47759fa464349907c3e1809f8adf6","parentId":null,"modified":1625509137737,"created":1625509137737,"name":"Sênior","description":"","scope":"collection","_type":"workspace"},{"_id":"req_23b1686510e641358b1ae196f2416381","parentId":"fld_a75ad14808044849921ea706216d4d7f","modified":1626805331893,"created":1626804842778,"url":"http://localhost:4999/api/filiais","name":"Filiais","description":"","method":"GET","body":{},"parameters":[{"name":"id","value":"1","id":"pair_07244d22e01940de9be2bb6b7c3e2086","disabled":true},{"name":"Base","value":"softran_termaco","id":"pair_72b54caf21d0436e85c70fcb5dbe447d","disabled":true},{"name":"codigo","value":"FOR","id":"pair_73a221a2a05245eb9d4c106c5d6f3f9b","disabled":false},{"name":"cid_codigo","value":"SPO","id":"pair_88f26f146f38441191c938d33b4bb2cf","disabled":true}],"headers":[],"authentication":{},"metaSortKey":-1626629934686,"isPrivate":false,"settingStoreCookies":true,"settingSendCookies":true,"settingDisableRenderRequestBody":false,"settingEncodeUrl":true,"settingRebuildPath":true,"settingFollowRedirects":"global","_type":"request"},{"_id":"req_36709d16165a48c5b42c7b282912d8c7","parentId":"fld_a75ad14808044849921ea706216d4d7f","modified":1627406557854,"created":1627406537826,"url":"http://localhost:4999/api/produtostransportados","name":"Produtos Transportados","description":"","method":"GET","body":{},"parameters":[{"name":"Base","value":"softran_termaco","id":"pair_72b54caf21d0436e85c70fcb5dbe447d","disabled":false}],"headers":[],"authentication":{},"metaSortKey":-1626608703786,"isPrivate":false,"settingStoreCookies":true,"settingSendCookies":true,"settingDisableRenderRequestBody":false,"settingEncodeUrl":true,"settingRebuildPath":true,"settingFollowRedirects":"global","_type":"request"},{"_id":"req_5436c0fa5ef9475ebba352f534c72d97","parentId":"fld_a75ad14808044849921ea706216d4d7f","modified":1627317099399,"created":1626899419055,"url":"http://localhost:4999/api/steptracker","name":"Step Tracker (CTRC)","description":"","method":"GET","body":{},"parameters":[{"name":"Base","value":"softran_termaco","id":"pair_c979be3a13f14a8c84a0b1c12bac8f61"},{"name":"tipo","value":"CTRC","id":"pair_5d30192d3ea9453882b1ba45241d59c0"},{"name":"cnpj","value":"89674782001391","id":"pair_6983d0c406d44af9a5bcf4581a471b05","disabled":true},{"name":"documento","value":"SPOE4183","id":"pair_afaf53979c194d8ea2edefeab6dbbc64"}],"headers":[],"authentication":{},"metaSortKey":-1626587472886,"isPrivate":false,"settingStoreCookies":true,"settingSendCookies":true,"settingDisableRenderRequestBody":false,"settingEncodeUrl":true,"settingRebuildPath":true,"settingFollowRedirects":"global","_type":"request"},{"_id":"req_202bc0f834bc43c5a16d2f68cd5dd46c","parentId":"fld_a75ad14808044849921ea706216d4d7f","modified":1627317126723,"created":1626959640845,"url":"http://localhost:4999/api/steptracker","name":"Step Tracker (NF)","description":"","method":"GET","body":{},"parameters":[{"name":"Base","value":"softran_termaco","id":"pair_c979be3a13f14a8c84a0b1c12bac8f61"},{"name":"tipo","value":"NF","id":"pair_5d30192d3ea9453882b1ba45241d59c0"},{"name":"cnpj","value":"89674782001391","id":"pair_6983d0c406d44af9a5bcf4581a471b05","disabled":false},{"name":"documento","value":"1517772","id":"pair_afaf53979c194d8ea2edefeab6dbbc64"}],"headers":[],"authentication":{},"metaSortKey":-1626566241986,"isPrivate":false,"settingStoreCookies":true,"settingSendCookies":true,"settingDisableRenderRequestBody":false,"settingEncodeUrl":true,"settingRebuildPath":true,"settingFollowRedirects":"global","_type":"request"},{"_id":"req_426123535f3d490fbeee7265f364976d","parentId":"fld_a75ad14808044849921ea706216d4d7f","modified":1626811690687,"created":1626811387317,"url":"http://localhost:4999/api/listafiliaiscliente","name":"Filiais do Cliente","description":"","method":"GET","body":{},"parameters":[{"name":"cnpj","value":"16851732000206","id":"pair_5b18aa21111e4217a349626d50f1c279"},{"id":"pair_b5e2c76674c94fa2a2fffef4b423e305","name":"Base","value":"softran_termaco","description":"","disabled":true}],"headers":[],"authentication":{},"metaSortKey":-1626545011086,"isPrivate":false,"settingStoreCookies":true,"settingSendCookies":true,"settingDisableRenderRequestBody":false,"settingEncodeUrl":true,"settingRebuildPath":true,"settingFollowRedirects":"global","_type":"request"},{"_id":"req_bec281f00721440b90ec9ba0f092bd82","parentId":"fld_a75ad14808044849921ea706216d4d7f","modified":1627316530128,"created":1627305836436,"url":"http://localhost:4999/api/cidadesatendidas","name":"Cidades Atendidas","description":"","method":"GET","body":{},"parameters":[{"id":"pair_b5e2c76674c94fa2a2fffef4b423e305","name":"Base","value":"softran_termaco","description":"","disabled":true},{"name":"uf","value":"CE","id":"pair_5b18aa21111e4217a349626d50f1c279"},{"id":"pair_53796f4a29a249afaee82b566d1d2c79","name":"cidade","value":"ARACATI","description":""}],"headers":[],"authentication":{},"metaSortKey":-1626502549286,"isPrivate":false,"settingStoreCookies":true,"settingSendCookies":true,"settingDisableRenderRequestBody":false,"settingEncodeUrl":true,"settingRebuildPath":true,"settingFollowRedirects":"global","_type":"request"},{"_id":"req_73dcb6efb154493fb4e5d339adb2158a","parentId":"fld_a75ad14808044849921ea706216d4d7f","modified":1627591299063,"created":1627591254542,"url":"http://localhost:4999/api/posicaocargaapp","name":"Posição Carga APP","description":"","method":"GET","body":{},"parameters":[{"name":"dt_inicial","value":"2021-05-01"},{"name":"dt_final","value":"2021-05-12"},{"name":"notafiscal","value":"47486"},{"name":"ctrc","value":"SPOE3257805"},{"name":"pagina_nro","value":"1"},{"name":"pagina_tam","value":"50"}],"headers":[],"authentication":{},"metaSortKey":-1626491933836,"isPrivate":false,"settingStoreCookies":true,"settingSendCookies":true,"settingDisableRenderRequestBody":false,"settingEncodeUrl":true,"settingRebuildPath":true,"settingFollowRedirects":"global","_type":"request"},{"_id":"req_8a260d1db235402aa2bbde26aa89ac5e","parentId":"fld_a75ad14808044849921ea706216d4d7f","modified":1627316683805,"created":1627316585292,"url":"http://localhost:4999/api/cidadesatendidasPOST","name":"Cidades Atendidas","description":"","method":"POST","body":{"mimeType":"application/json","text":"{\n\t\"uf\": \"CE\",\n  \"cidade\": \"ARACATI\"\n}"},"parameters":[],"headers":[{"name":"Content-Type","value":"application/json","id":"pair_27b0f553f49e4fa69c0fb583fa2bb7d4"}],"authentication":{},"metaSortKey":-1626481318386,"isPrivate":false,"settingStoreCookies":true,"settingSendCookies":true,"settingDisableRenderRequestBody":false,"settingEncodeUrl":true,"settingRebuildPath":true,"settingFollowRedirects":"global","_type":"request"},{"_id":"req_8d03840cb11946438092259de2ce6356","parentId":"fld_1daf88690979415a8beb37af0f8185db","modified":1626785168529,"created":1626460087486,"url":"http://localhost:4999/api/apiCliente","name":"apiCliente_GET","description":"","method":"GET","body":{},"parameters":[{"id":"pair_a65fa41b33fc4c95a31856c5739048d9","name":"chaveNFe","value":"35210689674782001391550010015177721007675588","description":""}],"headers":[],"authentication":{},"metaSortKey":-1626460087486,"isPrivate":false,"settingStoreCookies":true,"settingSendCookies":true,"settingDisableRenderRequestBody":false,"settingEncodeUrl":true,"settingRebuildPath":true,"settingFollowRedirects":"global","_type":"request"},{"_id":"fld_1daf88690979415a8beb37af0f8185db","parentId":"wrk_c8a47759fa464349907c3e1809f8adf6","modified":1626460060408,"created":1626460060408,"name":"API","description":"","environment":{},"environmentPropertyOrder":null,"metaSortKey":-1626460060408,"_type":"request_group"},{"_id":"req_8c0f7a0d25ff40e389bef6093a6e96f3","parentId":"fld_1daf88690979415a8beb37af0f8185db","modified":1626465719349,"created":1626463821967,"url":"http://localhost:4999/api/apiCliente","name":"apiCliente_POST","description":"","method":"POST","body":{"mimeType":"application/json","text":"{\n    \"valoresParametros\":[ \"89674782001391\",\"1517772\",\"1\"]\n}"},"parameters":[],"headers":[{"name":"Content-Type","value":"application/json","id":"pair_8c5c59b6938a4498abde4d0c8090eb33"}],"authentication":{},"metaSortKey":-1626222355612.25,"isPrivate":false,"settingStoreCookies":true,"settingSendCookies":true,"settingDisableRenderRequestBody":false,"settingEncodeUrl":true,"settingRebuildPath":true,"settingFollowRedirects":"global","_type":"request"},{"_id":"req_04bced8d3d4d445abc816985f12dceb8","parentId":"fld_1daf88690979415a8beb37af0f8185db","modified":1627580571525,"created":1626785981731,"url":"http://localhost:4999/api/apiTracking","name":"apiTracking_POST","description":"","method":"POST","body":{"mimeType":"application/json","text":"{\n    \"valoresParametros\":[ \"92660406000976\",\"387613\",\"5\"]\n}"},"parameters":[],"headers":[{"name":"Content-Type","value":"application/json","id":"pair_8c5c59b6938a4498abde4d0c8090eb33"}],"authentication":{},"metaSortKey":-1626103489675.375,"isPrivate":false,"settingStoreCookies":true,"settingSendCookies":true,"settingDisableRenderRequestBody":false,"settingEncodeUrl":true,"settingRebuildPath":true,"settingFollowRedirects":"global","_type":"request"},{"_id":"req_6c05c1d77f684bf5a123831c717ff138","parentId":"fld_1daf88690979415a8beb37af0f8185db","modified":1626893809204,"created":1626461998702,"url":"http://localhost:4999/api/apiDados","name":"apiDados_GET","description":"","method":"GET","body":{},"parameters":[{"id":"pair_a65fa41b33fc4c95a31856c5739048d9","name":"NF_num","value":"14523","description":"","disabled":false},{"id":"pair_8085eeaeb07c444c8956f6f64eb27b42","name":"CTRC_num","value":"8","description":"","disabled":true}],"headers":[],"authentication":{},"metaSortKey":-1625984623738.5,"isPrivate":false,"settingStoreCookies":true,"settingSendCookies":true,"settingDisableRenderRequestBody":false,"settingEncodeUrl":true,"settingRebuildPath":true,"settingFollowRedirects":"global","_type":"request"},{"_id":"req_5a984e0b55ff4d0bb12a762896927a4f","parentId":"fld_7798714ccba7411ca60b186503103b97","modified":1626460025207,"created":1626267549242,"url":"http://192.168.1.139:4999/senior/motivoEntradaSaida","name":"motivoEntradaSaida_TEST","description":"","method":"GET","body":{},"parameters":[{"id":"pair_1249eedab7b845479cbd52079363ccad","name":"Base","value":"softran_termaco","description":"","disabled":true},{"id":"pair_f2c72e4941224bacae14b7eea1669df4","name":"Base","value":"softran_transporte","description":"","disabled":false},{"id":"pair_ea5d88cf70f04371adae4032b1183445","name":"CdMotivo","value":"1","description":"","disabled":true},{"id":"pair_2bc25550adaf49879a30d35e8df20cde","name":"help","value":"true","description":"","disabled":true}],"headers":[],"authentication":{"type":"bearer","token":"eyJhbGciOiJIUzI1NiIsInR5cCI6IkpXVCJ9.eyJDZEVtcHJlc2EiOjIwLCJEc0FwZWxpZG8iOiJTVVBFUlZJU09SIiwiaWF0IjoxNjI2MjY3MzM2LCJleHAiOjE2MjYzNTM3MzZ9.qt8xXdXsH70k4AOEdHPxMwP3cwEBxx3J4JrZc_FaBxg"},"metaSortKey":-1625509159816,"isPrivate":false,"settingStoreCookies":true,"settingSendCookies":true,"settingDisableRenderRequestBody":false,"settingEncodeUrl":true,"settingRebuildPath":true,"settingFollowRedirects":"global","_type":"request"},{"_id":"fld_7798714ccba7411ca60b186503103b97","parentId":"wrk_c8a47759fa464349907c3e1809f8adf6","modified":1626460028748,"created":1626267535195,"name":"Testes","description":"","environment":{},"environmentPropertyOrder":null,"metaSortKey":-1626459927786,"_type":"request_group"},{"_id":"req_0b478bc72f7c464bbf2969e8b4112456","parentId":"fld_7cad98cba9154f1690ade17e675a20e1","modified":1626459937047,"created":1625776028411,"url":"http://localhost:4999/senior/QRcode","name":"QRcode","description":"","method":"POST","body":{"mimeType":"application/json","text":"{\n\t\"data\": {\t\t\n\t\t\"NrPlaca\": \"XXX9999\"\n\t},\n\t\"cfg\": {\n\t\t\"type\": \"png\",\n\t\t\"size\": 10,\n\t\t\"margin\": 1 \n\t}\n}"},"parameters":[],"headers":[{"name":"Content-Type","value":"application/json","id":"pair_1ba0d1404c6b4702873a83efb6be3d5a"}],"authentication":{"type":"bearer","token":"eyJhbGciOiJIUzI1NiIsInR5cCI6IkpXVCJ9.eyJDZEVtcHJlc2EiOjIwLCJEc0FwZWxpZG8iOiJTVVBFUlZJU09SIiwiaWF0IjoxNjI1NzczMjY1LCJleHAiOjE2MjU4NTk2NjV9.OKYgwSGN-PxCg1GOtiSqU--0581snYKUxiGHSAbj-ik"},"metaSortKey":-1625509159991,"isPrivate":false,"settingStoreCookies":true,"settingSendCookies":true,"settingDisableRenderRequestBody":false,"settingEncodeUrl":true,"settingRebuildPath":true,"settingFollowRedirects":"global","_type":"request"},{"_id":"fld_7cad98cba9154f1690ade17e675a20e1","parentId":"wrk_c8a47759fa464349907c3e1809f8adf6","modified":1626459927736,"created":1626459927736,"name":"Patio","description":"","environment":{},"environmentPropertyOrder":null,"metaSortKey":-1626459927736,"_type":"request_group"},{"_id":"req_bad9596648ff406292b78dd6349030ab","parentId":"fld_7cad98cba9154f1690ade17e675a20e1","modified":1626459941027,"created":1625837230868,"url":"http://localhost:4999/senior/QRcode","name":"QRcode","description":"","method":"GET","body":{},"parameters":[{"id":"pair_6befa40ee0b644878daf69605ae578b4","name":"NrPlaca","value":"POC1909","description":""},{"id":"pair_1df8b9b4747147bc8d2cac2aa7e9cbe6","name":"type","value":"png","description":""},{"id":"pair_3dfa1cd4ed73455784a2b39cfd52954a","name":"size","value":"10","description":""},{"id":"pair_548ed80061e94e01a43486c842bba02c","name":"margin","value":"1","description":""}],"headers":[],"authentication":{},"metaSortKey":-1625509159941,"isPrivate":false,"settingStoreCookies":true,"settingSendCookies":true,"settingDisableRenderRequestBody":false,"settingEncodeUrl":true,"settingRebuildPath":true,"settingFollowRedirects":"global","_type":"request"},{"_id":"req_a4463c9536154a03b69d05e87887b112","parentId":"fld_7cad98cba9154f1690ade17e675a20e1","modified":1626459943420,"created":1625751374891,"url":"http://localhost:4999/senior/tokenControlePatio","name":"token ( Controle Patio )","description":"","method":"POST","body":{"mimeType":"application/json","text":"{\n\t\"CdEmpresa\":         20, \n\t\"DsApelido\":         \"SUPERVISOR\",\n\t\"DsSenha\":           \"123456\"\n}\n"},"parameters":[],"headers":[{"name":"Content-Type","value":"application/json","id":"pair_0290b8cfcf9740ef9a192e7192aa5d08"}],"authentication":{},"metaSortKey":-1625509159891,"isPrivate":false,"settingStoreCookies":true,"settingSendCookies":true,"settingDisableRenderRequestBody":false,"settingEncodeUrl":true,"settingRebuildPath":true,"settingFollowRedirects":"global","_type":"request"},{"_id":"req_f54ce30222da4a57928359f542e93bea","parentId":"fld_7cad98cba9154f1690ade17e675a20e1","modified":1626459964619,"created":1625514023748,"url":"http://localhost:4999/senior/funcionario","name":"funcionario","description":"","method":"GET","body":{},"parameters":[{"id":"pair_1249eedab7b845479cbd52079363ccad","name":"Base","value":"softran_termaco","description":"","disabled":false},{"id":"pair_f2c72e4941224bacae14b7eea1669df4","name":"Base","value":"softran_transporte","description":"","disabled":true},{"id":"pair_b016020e14e84babb98c14de1011a88d","name":"NrCpf","value":"36230910306","description":"","disabled":true},{"id":"pair_ea5d88cf70f04371adae4032b1183445","name":"CdFuncionario","value":"5529","description":"","disabled":false},{"id":"pair_560274ccfbe0471f9978fbb2da986d94","name":"help","value":"true","description":"","disabled":true}],"headers":[],"authentication":{"type":"bearer","token":"eyJhbGciOiJIUzI1NiIsInR5cCI6IkpXVCJ9.eyJDZEVtcHJlc2EiOjIwLCJEc0FwZWxpZG8iOiJTVVBFUlZJU09SIiwiaWF0IjoxNjI2MTgxNjU1LCJleHAiOjE2MjYyNjgwNTV9.hASdCcqqnw3gX84Y0XgM8pnVaNuwt32EEAnMfraOFfw"},"metaSortKey":-1625509159866,"isPrivate":false,"settingStoreCookies":true,"settingSendCookies":true,"settingDisableRenderRequestBody":false,"settingEncodeUrl":true,"settingRebuildPath":true,"settingFollowRedirects":"global","_type":"request"},{"_id":"req_97d155ff715940efa21b0f61a0620db4","parentId":"fld_7cad98cba9154f1690ade17e675a20e1","modified":1626459966863,"created":1625581840109,"url":"http://localhost:4999/senior/usuario","name":"usuário","description":"","method":"GET","body":{},"parameters":[{"id":"pair_1249eedab7b845479cbd52079363ccad","name":"Base","value":"softran_termaco","description":"","disabled":false},{"id":"pair_f2c72e4941224bacae14b7eea1669df4","name":"Base","value":"softran_transporte","description":"","disabled":true},{"id":"pair_b016020e14e84babb98c14de1011a88d","name":"DsApelido","value":"SUPERVISOR","description":"","disabled":false},{"id":"pair_ea5d88cf70f04371adae4032b1183445","name":"CdFuncionario","value":"5814","description":"","disabled":true},{"id":"pair_560274ccfbe0471f9978fbb2da986d94","name":"help","value":"true","description":"","disabled":true}],"headers":[],"authentication":{"type":"bearer","token":"eyJhbGciOiJIUzI1NiIsInR5cCI6IkpXVCJ9.eyJDZEVtcHJlc2EiOjIwLCJEc0FwZWxpZG8iOiJTVVBFUlZJU09SIiwiaWF0IjoxNjI2MTgxNjU1LCJleHAiOjE2MjYyNjgwNTV9.hASdCcqqnw3gX84Y0XgM8pnVaNuwt32EEAnMfraOFfw"},"metaSortKey":-1625509159853.5,"isPrivate":false,"settingStoreCookies":true,"settingSendCookies":true,"settingDisableRenderRequestBody":false,"settingEncodeUrl":true,"settingRebuildPath":true,"settingFollowRedirects":"global","_type":"request"},{"_id":"req_25ae9e716d5d40f48ff34658c494131c","parentId":"fld_7cad98cba9154f1690ade17e675a20e1","modified":1626459978508,"created":1625510469157,"url":"http://localhost:4999/senior/empresa","name":"empresa","description":"","method":"GET","body":{},"parameters":[{"id":"pair_1249eedab7b845479cbd52079363ccad","name":"Base","value":"softran_termaco","description":"","disabled":false},{"id":"pair_f2c72e4941224bacae14b7eea1669df4","name":"Base","value":"softran_transporte","description":"","disabled":true},{"id":"pair_ea5d88cf70f04371adae4032b1183445","name":"CDEMPRESA","value":"20","description":"","disabled":false},{"id":"pair_2bc25550adaf49879a30d35e8df20cde","name":"help","value":"true","description":"","disabled":true}],"headers":[],"authentication":{"type":"bearer","token":"eyJhbGciOiJIUzI1NiIsInR5cCI6IkpXVCJ9.eyJDZEVtcHJlc2EiOjIwLCJEc0FwZWxpZG8iOiJTVVBFUlZJU09SIiwiaWF0IjoxNjI1NzczMjY1LCJleHAiOjE2MjU4NTk2NjV9.OKYgwSGN-PxCg1GOtiSqU--0581snYKUxiGHSAbj-ik"},"metaSortKey":-1625509159847.25,"isPrivate":false,"settingStoreCookies":true,"settingSendCookies":true,"settingDisableRenderRequestBody":false,"settingEncodeUrl":true,"settingRebuildPath":true,"settingFollowRedirects":"global","_type":"request"},{"_id":"req_586c723e612a4bd58c3f865cb5ac36b9","parentId":"fld_7cad98cba9154f1690ade17e675a20e1","modified":1626459981274,"created":1625577487555,"url":"http://localhost:4999/senior/motivoEntradaSaida","name":"motivoEntradaSaida","description":"","method":"GET","body":{},"parameters":[{"id":"pair_1249eedab7b845479cbd52079363ccad","name":"Base","value":"softran_termaco","description":"","disabled":true},{"id":"pair_f2c72e4941224bacae14b7eea1669df4","name":"Base","value":"softran_transporte","description":"","disabled":false},{"id":"pair_ea5d88cf70f04371adae4032b1183445","name":"CdMotivo","value":"1","description":"","disabled":true},{"id":"pair_2bc25550adaf49879a30d35e8df20cde","name":"help","value":"true","description":"","disabled":true}],"headers":[],"authentication":{"type":"bearer","token":"eyJhbGciOiJIUzI1NiIsInR5cCI6IkpXVCJ9.eyJDZEVtcHJlc2EiOjIwLCJEc0FwZWxpZG8iOiJTVVBFUlZJU09SIiwiaWF0IjoxNjI2MjY5Njg4LCJleHAiOjE2MjYzNTYwODh9.eLx0dbqeSdb2LW2QBf_hrKP9Hmi95f7fjPIPrV4avx4"},"metaSortKey":-1625509159844.125,"isPrivate":false,"settingStoreCookies":true,"settingSendCookies":true,"settingDisableRenderRequestBody":false,"settingEncodeUrl":true,"settingRebuildPath":true,"settingFollowRedirects":"global","_type":"request"},{"_id":"req_2625ae29b322422baf88354ed71dc771","parentId":"fld_7cad98cba9154f1690ade17e675a20e1","modified":1626459983846,"created":1625513159428,"url":"http://localhost:4999/senior/veiculo","name":"veiculo","description":"","method":"GET","body":{},"parameters":[{"id":"pair_ea5d88cf70f04371adae4032b1183445","name":"NrPlaca","value":"POC1909","description":"","disabled":false},{"id":"pair_2bc25550adaf49879a30d35e8df20cde","name":"help","value":"true","description":"","disabled":true}],"headers":[],"authentication":{"type":"bearer","token":"eyJhbGciOiJIUzI1NiIsInR5cCI6IkpXVCJ9.eyJDZEVtcHJlc2EiOjIwLCJEc0FwZWxpZG8iOiJTVVBFUlZJU09SIiwiaWF0IjoxNjI2MjkxODc1LCJleHAiOjE2MjYzNzgyNzV9.QEI2gescdtLZCVLgpNDls6rlnMqadfehDgg2SE-LX1Y"},"metaSortKey":-1625509159842.5625,"isPrivate":false,"settingStoreCookies":true,"settingSendCookies":true,"settingDisableRenderRequestBody":false,"settingEncodeUrl":true,"settingRebuildPath":true,"settingFollowRedirects":"global","_type":"request"},{"_id":"req_100fe59da18f48e794824af4f869cbc2","parentId":"fld_7cad98cba9154f1690ade17e675a20e1","modified":1626459948127,"created":1625509159890,"url":"http://localhost:4999/senior/motorista","name":"motorista","description":"","method":"GET","body":{},"parameters":[{"id":"pair_1249eedab7b845479cbd52079363ccad","name":"Base","value":"softran_termaco","description":"","disabled":true},{"id":"pair_f2c72e4941224bacae14b7eea1669df4","name":"Base","value":"softran_transporte","description":"","disabled":false},{"id":"pair_ea5d88cf70f04371adae4032b1183445","name":"NrCPF","value":"00046579001372","description":"","disabled":false},{"id":"pair_560274ccfbe0471f9978fbb2da986d94","name":"help","value":"true","description":"","disabled":true}],"headers":[],"authentication":{"type":"bearer","token":"eyJhbGciOiJIUzI1NiIsInR5cCI6IkpXVCJ9.eyJDZEVtcHJlc2EiOjIwLCJEc0FwZWxpZG8iOiJTVVBFUlZJU09SIiwiaWF0IjoxNjI1NzczMjY1LCJleHAiOjE2MjU4NTk2NjV9.OKYgwSGN-PxCg1GOtiSqU--0581snYKUxiGHSAbj-ik"},"metaSortKey":-1625509159841,"isPrivate":false,"settingStoreCookies":true,"settingSendCookies":true,"settingDisableRenderRequestBody":false,"settingEncodeUrl":true,"settingRebuildPath":true,"settingFollowRedirects":"global","_type":"request"},{"_id":"req_14c2555f392842fea2de81280aff34ba","parentId":"fld_7cad98cba9154f1690ade17e675a20e1","modified":1626459996231,"created":1625516645239,"url":"http://localhost:4999/senior/veiculoEntradaSaida","name":"veiculo - ( Entrada & Saida )","description":"","method":"GET","body":{},"parameters":[{"id":"pair_1249eedab7b845479cbd52079363ccad","name":"Base","value":"softran_termaco","description":"","disabled":true},{"id":"pair_f2c72e4941224bacae14b7eea1669df4","name":"Base","value":"softran_transporte","description":"","disabled":false},{"id":"pair_a7f13bae54db4843b11b49990dcc45a8","name":"CdVeiculo","value":"170902","description":"","disabled":true},{"id":"pair_ea5d88cf70f04371adae4032b1183445","name":"NrPlaca","value":"POC1909","description":"","disabled":true},{"id":"pair_44fd57b48d6e498196c76a8064d8c523","name":"DtInicial","value":"2021-07-06 00:00:00","description":""},{"id":"pair_6ff3ec2a3921495992589d7cc0f909bb","name":"DtFinal","value":"2021-07-06 23:59:59","description":""},{"id":"pair_2bc25550adaf49879a30d35e8df20cde","name":"help","value":"true","description":"","disabled":true}],"headers":[],"authentication":{"type":"bearer","token":"eyJhbGciOiJIUzI1NiIsInR5cCI6IkpXVCJ9.eyJDZEVtcHJlc2EiOjIwLCJEc0FwZWxpZG8iOiJTVVBFUlZJU09SIiwiaWF0IjoxNjI1NzczMjY1LCJleHAiOjE2MjU4NTk2NjV9.OKYgwSGN-PxCg1GOtiSqU--0581snYKUxiGHSAbj-ik"},"metaSortKey":-1625509159828.5,"isPrivate":false,"settingStoreCookies":true,"settingSendCookies":true,"settingDisableRenderRequestBody":false,"settingEncodeUrl":true,"settingRebuildPath":true,"settingFollowRedirects":"global","_type":"request"},{"_id":"req_7256189ddf904e1b938c047f414bd7f2","parentId":"fld_7cad98cba9154f1690ade17e675a20e1","modified":1626460002574,"created":1625576949867,"url":"http://localhost:4999/senior/veiculoPosicaoAtual","name":"veiculo - ( Posição Atual )","description":"","method":"GET","body":{},"parameters":[{"id":"pair_1249eedab7b845479cbd52079363ccad","name":"Base","value":"softran_termaco","description":"","disabled":true},{"id":"pair_f2c72e4941224bacae14b7eea1669df4","name":"Base","value":"softran_transporte","description":"","disabled":false},{"id":"pair_a7f13bae54db4843b11b49990dcc45a8","name":"CdVeiculo","value":"170902","description":"","disabled":true},{"id":"pair_ea5d88cf70f04371adae4032b1183445","name":"NrPlaca","value":"POC1909","description":"","disabled":false},{"id":"pair_2bc25550adaf49879a30d35e8df20cde","name":"help","value":"true","description":"","disabled":true}],"headers":[],"authentication":{"type":"bearer","token":"\"eyJhbGciOiJIUzI1NiIsInR5cCI6IkpXVCJ9.eyJDZEVtcHJlc2EiOjIwLCJEc0FwZWxpZG8iOiJTVVBFUlZJU09SIiwiaWF0IjoxNjI2MzcwMzY5LCJleHAiOjE2MjY0NTY3Njl9.CorfV8U1Sq5kZXnlMPIoJkxfj6TFsLR0Vmq_bntYUOo"},"metaSortKey":-1625509159822.25,"isPrivate":false,"settingStoreCookies":true,"settingSendCookies":true,"settingDisableRenderRequestBody":false,"settingEncodeUrl":true,"settingRebuildPath":true,"settingFollowRedirects":"global","_type":"request"},{"_id":"req_6b997cbe263c4b2e8f77c7c374f3cf9a","parentId":"fld_7cad98cba9154f1690ade17e675a20e1","modified":1626459987916,"created":1625601574433,"url":"http://localhost:4999/senior/veiculoRegistraES","name":"veiculo - ( Registro ES )","description":"","method":"POST","body":{"mimeType":"application/json","text":"{\n\t\"Base\":              \"softran_transporte\",\n\t\"TpMovimento\":       \"S\",\n\t\"CdEmpresa\":         20, \n\t\"InEntradaSaida\":    1, \n  \"CdFuncionario\":     5814, \n\t\"NrPlaca\":           \"POC1909\",\n\t\"CdMotorista\":       \"00046579001372\",\n\t\"InTpVeiculo\":       0, \n\t\"NrHodEntradaSaida\": 705110, \n  \"DsVeiculo\":         \"CAMPO DESCRIÇÃO\", \n\t\"CdMotivo\":          3, \n\t\"DsObs\":             \"CAMPO OBSERVAÇÃO - TESTE (15/07/2021 10:38)\", \n  \"InCarregado\":       1\n}\n"},"parameters":[],"headers":[{"name":"Content-Type","value":"application/json","id":"pair_0290b8cfcf9740ef9a192e7192aa5d08"}],"authentication":{"type":"bearer","token":"eyJhbGciOiJIUzI1NiIsInR5cCI6IkpXVCJ9.eyJDZEVtcHJlc2EiOjIwLCJEc0FwZWxpZG8iOiJTVVBFUlZJU09SIiwiaWF0IjoxNjI2MjkxODc1LCJleHAiOjE2MjYzNzgyNzV9.QEI2gescdtLZCVLgpNDls6rlnMqadfehDgg2SE-LX1Y"},"metaSortKey":-1625509159791,"isPrivate":false,"settingStoreCookies":true,"settingSendCookies":true,"settingDisableRenderRequestBody":false,"settingEncodeUrl":true,"settingRebuildPath":true,"settingFollowRedirects":"global","_type":"request"},{"_id":"env_ba1df1188bf2b8fefa57faf8073810104c23470b","parentId":"wrk_c8a47759fa464349907c3e1809f8adf6","modified":1625509138255,"created":1625509138255,"name":"Base Environment","data":{},"dataPropertyOrder":null,"color":null,"isPrivate":false,"metaSortKey":1625509138255,"_type":"environment"},{"_id":"jar_ba1df1188bf2b8fefa57faf8073810104c23470b","parentId":"wrk_c8a47759fa464349907c3e1809f8adf6","modified":1625509138285,"created":1625509138286,"name":"Default Jar","cookies":[],"_type":"cookie_jar"},{"_id":"spc_c5dbf2d0599340e3ac252a6f4eb91dc7","parentId":"wrk_c8a47759fa464349907c3e1809f8adf6","modified":1625509137743,"created":1625509137743,"fileName":"Sênior","contents":"","contentType":"yaml","_type":"api_spec"}]}